[
    {
        "id": 1,
        "picture": "http://placehold.it/32x32",
        "userPicture": "http://placehold.it/32x32",
        "userRating": 3.3791,
        "yearOfExperience": 9,
        "name": "Francis Johnston",
        "userName": "Santos Melendez",
        "userGender": "male",
        "Gender": "male",
        "company": "LOTRON",
        "email": "santosmelendez@lotron.com",
        "phone": "+1 (838) 555-3069",
        "address": "857 Grimes Road, Hickory, Michigan",
        "about": "Aliqua aliqua do cillum qui id id incididunt eu eu sint magna. Eiusmod consectetur velit elit excepteur pariatur sint excepteur esse. Non dolor sunt occaecat ad officia. Nulla tempor reprehenderit id labore nostrud.\r\n",
        "userComment": "Est ipsum officia id dolore laboris enim reprehenderit veniam labore. Incididunt proident aute occaecat mollit aliquip sint est excepteur exercitation tempor ea. Qui ad reprehenderit dolore dolore do laboris et.\r\n",
        "numberOfRecife": 14,
        "like": 418,
        "eventDate": "2014-05-14T03:16:35 -06:00",
        "foodName": "Britney Acevedo",
        "newsTitle": "Lola Paul",
        "recipeTypes1": [
          {
            "ingredients": [
              "nostrud",
              "in",
              "pariatur",
              "aliquip",
              "aliqua"
            ],
            "recipeName": "Robles Jordan",
            "cookingMethos": "Ut eu consequat velit ad. Ipsum magna laborum dolore aute labore nostrud nostrud exercitation mollit quis ex non. In dolore ad culpa commodo consequat sit ut voluptate occaecat adipisicing ex culpa aliquip ad. Fugiat exercitation sint et Lorem Lorem culpa cillum eiusmod magna pariatur ut officia. Irure fugiat eiusmod commodo esse non cillum et.\r\n",
            "rating": 3.7919
          }
        ],
        "recipeTypes2": [
          {
            "ingredients": [
              "qui",
              "culpa",
              "in",
              "culpa",
              "commodo"
            ],
            "recipeName": "Amber Turner",
            "cookingMethos": "Deserunt incididunt voluptate id voluptate velit tempor ut velit irure proident anim anim in. Velit cillum do cupidatat et occaecat amet minim eu irure aliqua. Eiusmod occaecat fugiat ut reprehenderit ad ipsum eu.\r\n",
            "rating": 3.5615
          }
        ],
        "recipeTypes3": [
          {
            "ingredients": [
              "consectetur",
              "culpa",
              "culpa",
              "nisi",
              "esse"
            ],
            "recipeName": "Goodwin Singleton",
            "cookingMethos": "Labore incididunt irure sit cupidatat proident. Dolore pariatur proident duis minim incididunt amet officia excepteur tempor. Reprehenderit adipisicing magna et ea excepteur reprehenderit labore tempor est Lorem magna ad nulla. Pariatur reprehenderit laborum ad aute voluptate aliqua ipsum labore ipsum officia sint mollit. Nisi aliqua eiusmod occaecat eiusmod culpa mollit ullamco cupidatat. Id anim magna nisi proident pariatur ullamco ad.\r\n",
            "rating": 3.909
          }
        ]
      },
      {
        "id": 2,
        "picture": "http://placehold.it/32x32",
        "userPicture": "http://placehold.it/32x32",
        "userRating": 3.2338,
        "yearOfExperience": 7,
        "name": "Lester Banks",
        "userName": "Corine Silva",
        "userGender": "female",
        "Gender": "female",
        "company": "DIGIPRINT",
        "email": "corinesilva@digiprint.com",
        "phone": "+1 (837) 459-2054",
        "address": "370 Hunterfly Place, Geyserville, Minnesota",
        "about": "Adipisicing dolor proident dolore eu dolor eu magna pariatur nostrud id commodo excepteur. Et laboris deserunt minim cillum velit cillum amet cupidatat nulla ex commodo dolor magna sit. Dolore do excepteur incididunt nulla incididunt et est. Cillum voluptate sint commodo aliqua excepteur amet sunt proident. Mollit mollit ad Lorem cupidatat do ipsum cillum sunt irure do deserunt. Laborum duis non minim enim nulla ad dolore nostrud nulla.\r\n",
        "userComment": "Ea nostrud ullamco aliquip proident laborum ex aliqua aute pariatur culpa. Cupidatat qui sit minim ex consectetur dolore fugiat labore aliquip velit sint incididunt aliqua. Ad laborum mollit culpa aliquip cupidatat laborum exercitation non et cillum anim velit non. Eu Lorem esse adipisicing minim minim ut. Nostrud sit reprehenderit Lorem est voluptate. Esse velit duis nostrud incididunt officia in irure exercitation dolor anim cupidatat enim sint. Aliquip esse adipisicing irure exercitation irure ad excepteur id aute consectetur.\r\n",
        "numberOfRecife": 17,
        "like": 462,
        "eventDate": "2016-04-19T05:11:07 -06:00",
        "foodName": "Shawn Kerr",
        "newsTitle": "Bethany Foster",
        "recipeTypes1": [
          {
            "ingredients": [
              "consequat",
              "nisi",
              "nisi",
              "sunt",
              "eiusmod"
            ],
            "recipeName": "Kirk Parker",
            "cookingMethos": "Labore culpa cupidatat fugiat mollit sit et ut qui qui esse in enim nulla. Minim magna eiusmod nostrud exercitation tempor irure sunt. Dolor pariatur Lorem consequat ut veniam officia consequat magna veniam. Eiusmod aliqua eiusmod aliquip ipsum culpa nisi ex id. Veniam sunt elit consectetur incididunt deserunt aliquip ullamco cupidatat. Deserunt fugiat fugiat enim ut ad ex incididunt nulla consectetur duis ullamco ullamco ea. Pariatur mollit mollit in id labore magna.\r\n",
            "rating": 4.7194
          }
        ],
        "recipeTypes2": [
          {
            "ingredients": [
              "sint",
              "exercitation",
              "laborum",
              "irure",
              "cillum"
            ],
            "recipeName": "Tamera Bowman",
            "cookingMethos": "Aliquip ullamco sit occaecat culpa in. Labore enim adipisicing ea anim cupidatat cupidatat eiusmod occaecat ut magna in aliqua sint elit. Sint excepteur nulla ad reprehenderit do. Occaecat do deserunt cillum pariatur veniam.\r\n",
            "rating": 3.0471
          }
        ],
        "recipeTypes3": [
          {
            "ingredients": [
              "commodo",
              "duis",
              "ad",
              "quis",
              "sit"
            ],
            "recipeName": "Andrews Short",
            "cookingMethos": "Eu sint culpa nulla proident fugiat ex commodo adipisicing id aliquip in. Ex veniam amet nisi ut aute ullamco in elit cupidatat elit nulla. Ipsum aute ex id est minim nulla. Aute irure adipisicing dolor incididunt anim cillum consectetur aliqua tempor aliquip esse reprehenderit ut. Enim incididunt aute consectetur labore do sint nisi eiusmod dolore duis esse officia. Aute amet cillum elit et exercitation veniam aute consequat id. Ullamco consectetur nostrud voluptate esse magna dolore cupidatat aliquip.\r\n",
            "rating": 4.7518
          }
        ]
      },
      {
        "id": 3,
        "picture": "http://placehold.it/32x32",
        "userPicture": "http://placehold.it/32x32",
        "userRating": 3.8135,
        "yearOfExperience": 5,
        "name": "Chaney Austin",
        "userName": "Parsons Kane",
        "userGender": "male",
        "Gender": "male",
        "company": "GOKO",
        "email": "parsonskane@goko.com",
        "phone": "+1 (954) 487-3376",
        "address": "579 Coles Street, Zortman, Tennessee",
        "about": "Velit nisi tempor minim labore pariatur nostrud qui anim. Deserunt consectetur tempor anim dolor consectetur sint non incididunt. Voluptate ex dolor tempor ex dolor est qui magna nisi nulla cupidatat magna elit aute. Sunt eu in sint labore incididunt. Eiusmod elit consequat non reprehenderit et voluptate proident officia tempor.\r\n",
        "userComment": "Elit ut aliqua commodo nulla velit consequat reprehenderit non ullamco commodo et dolor mollit cillum. Id dolore deserunt id id magna officia aute ipsum dolor est. Quis nisi nulla excepteur veniam reprehenderit labore occaecat quis.\r\n",
        "numberOfRecife": 16,
        "like": 447,
        "eventDate": "2020-01-28T08:08:46 -06:00",
        "foodName": "Kathrine Sanders",
        "newsTitle": "Maldonado Harrison",
        "recipeTypes1": [
          {
            "ingredients": [
              "fugiat",
              "irure",
              "enim",
              "enim",
              "amet"
            ],
            "recipeName": "Waller Mcmahon",
            "cookingMethos": "In velit fugiat veniam nostrud aliquip duis qui ex ea anim consequat proident non. Dolor labore tempor aliquip non sunt irure est non esse tempor cillum. Eu ea nostrud voluptate officia elit aliqua officia consequat incididunt reprehenderit. Est esse ad consequat nostrud. Excepteur pariatur magna ex commodo nostrud consequat.\r\n",
            "rating": 3.2863
          }
        ],
        "recipeTypes2": [
          {
            "ingredients": [
              "mollit",
              "aute",
              "ex",
              "deserunt",
              "quis"
            ],
            "recipeName": "Keith Vaughan",
            "cookingMethos": "Nulla Lorem ad nostrud dolor occaecat dolor aute est. Fugiat enim consequat non qui ad officia et consectetur irure voluptate voluptate minim. Veniam dolore et pariatur ad.\r\n",
            "rating": 3.8373
          }
        ],
        "recipeTypes3": [
          {
            "ingredients": [
              "Lorem",
              "culpa",
              "sit",
              "deserunt",
              "amet"
            ],
            "recipeName": "Leticia Hansen",
            "cookingMethos": "Anim cupidatat sit adipisicing Lorem ipsum minim labore anim do eiusmod do proident. Fugiat officia proident laborum nisi consectetur sunt sit dolor. Aute et officia ipsum commodo voluptate fugiat ipsum adipisicing veniam qui tempor ipsum Lorem.\r\n",
            "rating": 4.358
          }
        ]
      },
      {
        "id": 4,
        "picture": "http://placehold.it/32x32",
        "userPicture": "http://placehold.it/32x32",
        "userRating": 4.9805,
        "yearOfExperience": 9,
        "name": "Knowles Trujillo",
        "userName": "Harmon Farley",
        "userGender": "male",
        "Gender": "male",
        "company": "AUSTEX",
        "email": "harmonfarley@austex.com",
        "phone": "+1 (992) 518-2177",
        "address": "905 Maple Street, Malott, Pennsylvania",
        "about": "Et incididunt voluptate enim ex pariatur eu sit officia. Cupidatat sit consequat proident reprehenderit elit sit in ullamco excepteur officia pariatur aliquip. Enim ipsum nulla adipisicing fugiat irure aute do cupidatat et aute officia non irure esse.\r\n",
        "userComment": "Occaecat ea veniam id duis enim. Qui proident nisi magna enim cupidatat Lorem occaecat. Deserunt voluptate esse laborum nostrud. Enim deserunt amet Lorem officia non mollit reprehenderit incididunt quis nisi quis dolore ad.\r\n",
        "numberOfRecife": 18,
        "like": 533,
        "eventDate": "2015-10-20T11:29:28 -06:00",
        "foodName": "Carter Burke",
        "newsTitle": "Peck Mendez",
        "recipeTypes1": [
          {
            "ingredients": [
              "do",
              "occaecat",
              "nulla",
              "minim",
              "duis"
            ],
            "recipeName": "Estela Riley",
            "cookingMethos": "Reprehenderit excepteur esse nostrud reprehenderit. Ex ut occaecat et quis laboris excepteur. Et laboris officia velit aliquip ad deserunt consequat est cupidatat velit proident consequat est exercitation. Incididunt pariatur qui sunt Lorem incididunt nostrud cillum minim voluptate minim velit. Anim et cillum ipsum et exercitation velit dolor commodo ut esse occaecat qui veniam. Dolore ex elit duis magna aliqua exercitation. Excepteur dolor incididunt dolor eu non.\r\n",
            "rating": 4.5289
          }
        ],
        "recipeTypes2": [
          {
            "ingredients": [
              "duis",
              "nulla",
              "aliqua",
              "deserunt",
              "qui"
            ],
            "recipeName": "Navarro Sheppard",
            "cookingMethos": "Aliqua aliquip et sit voluptate. Consequat occaecat minim dolor eiusmod nostrud amet nulla adipisicing tempor sunt duis elit et nulla. Magna veniam occaecat deserunt fugiat excepteur. Consectetur nostrud labore nostrud enim enim et culpa ullamco consectetur fugiat consequat. Laborum ut incididunt amet mollit dolore quis labore in velit exercitation elit amet excepteur.\r\n",
            "rating": 3.5568
          }
        ],
        "recipeTypes3": [
          {
            "ingredients": [
              "esse",
              "deserunt",
              "ad",
              "excepteur",
              "Lorem"
            ],
            "recipeName": "Faulkner Rice",
            "cookingMethos": "In non voluptate veniam incididunt qui mollit pariatur nulla magna ipsum. Et aute est consequat ipsum commodo amet sint anim duis ex. Non sint laborum ullamco duis voluptate et proident. Reprehenderit fugiat et qui id sit. Ex sunt do in ea voluptate nisi amet id dolor cupidatat et sint anim. Culpa qui occaecat aute excepteur sunt reprehenderit dolore ut.\r\n",
            "rating": 3.1186
          }
        ]
      },
      {
        "id": 5,
        "picture": "http://placehold.it/32x32",
        "userPicture": "http://placehold.it/32x32",
        "userRating": 3.2515,
        "yearOfExperience": 6,
        "name": "Stefanie Castaneda",
        "userName": "Rush Franks",
        "userGender": "male",
        "Gender": "male",
        "company": "QUAILCOM",
        "email": "rushfranks@quailcom.com",
        "phone": "+1 (990) 564-3098",
        "address": "380 Beaver Street, Hall, Montana",
        "about": "Eiusmod velit do dolor quis sunt dolor. Veniam laboris culpa voluptate sunt proident aliqua duis enim exercitation. In fugiat consectetur dolor cupidatat velit incididunt eiusmod id officia mollit culpa sunt et. Amet ad occaecat mollit ex Lorem veniam tempor. Consectetur exercitation exercitation id voluptate nostrud nostrud.\r\n",
        "userComment": "Laboris consequat eu et irure cupidatat ullamco minim. Deserunt sint quis id quis aute Lorem consequat voluptate commodo. Magna duis officia elit voluptate id.\r\n",
        "numberOfRecife": 16,
        "like": 549,
        "eventDate": "2021-10-20T11:58:51 -06:00",
        "foodName": "Schultz Collier",
        "newsTitle": "Merle Berg",
        "recipeTypes1": [
          {
            "ingredients": [
              "amet",
              "reprehenderit",
              "velit",
              "esse",
              "enim"
            ],
            "recipeName": "Blankenship Langley",
            "cookingMethos": "Nisi cupidatat do esse culpa ea irure laborum voluptate. Nisi eiusmod ex culpa veniam commodo aliquip aliquip aute do laborum. Anim ipsum velit amet ipsum cupidatat cupidatat aliqua do consectetur excepteur velit duis. Amet pariatur mollit culpa excepteur ullamco. Nostrud ut id occaecat duis irure.\r\n",
            "rating": 3.1829
          }
        ],
        "recipeTypes2": [
          {
            "ingredients": [
              "incididunt",
              "nulla",
              "ea",
              "consectetur",
              "officia"
            ],
            "recipeName": "Everett Madden",
            "cookingMethos": "Minim ea Lorem veniam ea laboris incididunt voluptate commodo officia esse eiusmod et ut. Commodo exercitation laboris occaecat proident Lorem sit in occaecat quis irure ipsum ipsum ex. Nulla nisi enim est dolore et eu sit officia irure velit. Enim nulla adipisicing do officia ipsum anim anim adipisicing velit ea. Anim magna commodo ut amet dolore do sunt consectetur laboris magna sit ut excepteur.\r\n",
            "rating": 4.1952
          }
        ],
        "recipeTypes3": [
          {
            "ingredients": [
              "incididunt",
              "excepteur",
              "cillum",
              "et",
              "anim"
            ],
            "recipeName": "Kay Ochoa",
            "cookingMethos": "In ad in exercitation officia. Consequat quis tempor incididunt id culpa eiusmod consequat pariatur. Laborum anim nulla sunt anim fugiat ex enim ullamco eu. Laboris minim elit laborum adipisicing. Nisi commodo dolor nulla id et Lorem eu cupidatat in tempor ipsum nulla laboris. Aute commodo consectetur irure enim quis laboris cillum adipisicing consequat ex eu velit. Amet nulla dolor duis laboris.\r\n",
            "rating": 3.6982
          }
        ]
      },
      {
        "id": 6,
        "picture": "http://placehold.it/32x32",
        "userPicture": "http://placehold.it/32x32",
        "userRating": 3.4405,
        "yearOfExperience": 5,
        "name": "Judy Gates",
        "userName": "Barbra Kelly",
        "userGender": "female",
        "Gender": "female",
        "company": "REALMO",
        "email": "barbrakelly@realmo.com",
        "phone": "+1 (872) 546-2034",
        "address": "526 Will Place, Cobbtown, Kansas",
        "about": "Anim ex non cillum minim sunt proident proident. Dolore reprehenderit aute eu deserunt aute pariatur duis reprehenderit velit eiusmod elit amet. Mollit minim irure dolore tempor sunt mollit Lorem ut. Duis fugiat sint ipsum esse do eu dolore aliqua amet. Lorem id adipisicing exercitation dolore nulla mollit ipsum culpa excepteur. Reprehenderit est tempor labore aliquip laborum voluptate aute adipisicing Lorem eu eiusmod. Proident aute minim officia enim eu deserunt tempor mollit labore eu occaecat anim ullamco ullamco.\r\n",
        "userComment": "Veniam fugiat culpa sint exercitation ullamco Lorem cillum nostrud dolor voluptate in aliquip minim eu. Culpa Lorem labore magna exercitation dolore mollit est duis aute id minim ut incididunt. Anim Lorem ad exercitation commodo dolor nostrud. Aute adipisicing consectetur ex qui ex aliquip commodo excepteur in incididunt sit. Quis duis mollit ullamco exercitation amet dolore irure. Irure eiusmod proident sit id culpa magna ex nulla nulla commodo aute do. Deserunt exercitation ea veniam veniam.\r\n",
        "numberOfRecife": 15,
        "like": 441,
        "eventDate": "2022-09-28T05:37:38 -06:00",
        "foodName": "Phillips Odonnell",
        "newsTitle": "Cochran Becker",
        "recipeTypes1": [
          {
            "ingredients": [
              "aliqua",
              "in",
              "pariatur",
              "aliquip",
              "laborum"
            ],
            "recipeName": "Estelle Ramsey",
            "cookingMethos": "Non nostrud excepteur ea cupidatat cillum proident irure proident. Et pariatur pariatur est ullamco proident excepteur nulla eu sit proident quis excepteur est velit. Velit cupidatat velit sunt elit. Lorem deserunt cillum do esse cillum sit voluptate do ullamco anim.\r\n",
            "rating": 3.5373
          }
        ],
        "recipeTypes2": [
          {
            "ingredients": [
              "et",
              "aute",
              "veniam",
              "est",
              "ullamco"
            ],
            "recipeName": "Hunter Melton",
            "cookingMethos": "Dolor id commodo excepteur ad aliqua tempor aliqua esse fugiat nisi et. Incididunt commodo nulla elit voluptate. Ipsum mollit consectetur commodo sunt ad occaecat dolor ullamco deserunt enim irure consectetur nulla.\r\n",
            "rating": 4.9922
          }
        ],
        "recipeTypes3": [
          {
            "ingredients": [
              "qui",
              "in",
              "dolore",
              "aliquip",
              "voluptate"
            ],
            "recipeName": "Jeannette Tyson",
            "cookingMethos": "Aliquip aute proident officia aute magna ex voluptate cupidatat ipsum. Culpa excepteur culpa proident quis. Labore do adipisicing ea excepteur culpa laborum labore mollit. Tempor pariatur excepteur cillum excepteur pariatur. Culpa commodo velit incididunt magna excepteur Lorem adipisicing et esse deserunt nisi. Ea id dolor cillum enim adipisicing laborum qui. In id cillum exercitation in.\r\n",
            "rating": 4.7554
          }
        ]
      },
      {
        "id": 7,
        "picture": "http://placehold.it/32x32",
        "userPicture": "http://placehold.it/32x32",
        "userRating": 4.9575,
        "yearOfExperience": 10,
        "name": "Beach Morton",
        "userName": "Colleen Page",
        "userGender": "female",
        "Gender": "female",
        "company": "ZIDOX",
        "email": "colleenpage@zidox.com",
        "phone": "+1 (978) 418-2401",
        "address": "672 Grand Street, Riverton, Georgia",
        "about": "Officia nostrud nostrud anim eu dolor ad esse nisi aliqua adipisicing anim occaecat qui. Occaecat tempor qui do dolor dolor magna qui. Eu nisi dolore nostrud veniam culpa ut mollit ipsum. Veniam irure non adipisicing enim anim aliquip nulla fugiat. Est minim excepteur labore proident duis eiusmod id minim exercitation. Nulla cupidatat pariatur cupidatat occaecat ullamco. Eu voluptate elit magna voluptate esse aliqua qui sit eu consectetur sit ut dolor pariatur.\r\n",
        "userComment": "Sunt aliquip occaecat do consectetur eu qui elit non duis laboris officia aliquip mollit. Cillum enim laborum sunt non ut veniam sit sint culpa minim. Esse ullamco incididunt ad aute velit minim sit nostrud cupidatat dolor reprehenderit.\r\n",
        "numberOfRecife": 14,
        "like": 553,
        "eventDate": "2020-08-23T06:48:27 -06:00",
        "foodName": "Rosales Lara",
        "newsTitle": "Nichole Campbell",
        "recipeTypes1": [
          {
            "ingredients": [
              "sint",
              "laboris",
              "ut",
              "deserunt",
              "mollit"
            ],
            "recipeName": "Faith Booth",
            "cookingMethos": "Nulla esse excepteur nisi laboris exercitation. Qui veniam officia pariatur consectetur duis veniam adipisicing. Non veniam esse exercitation nulla. Sit esse occaecat culpa velit commodo qui.\r\n",
            "rating": 3.7685
          }
        ],
        "recipeTypes2": [
          {
            "ingredients": [
              "reprehenderit",
              "elit",
              "pariatur",
              "incididunt",
              "tempor"
            ],
            "recipeName": "Pugh Perez",
            "cookingMethos": "Non in proident esse aliqua reprehenderit adipisicing incididunt ex anim magna enim minim. Aliqua ipsum nostrud incididunt consequat sit adipisicing ullamco incididunt amet reprehenderit exercitation. Voluptate esse esse aliquip laborum ut fugiat deserunt est ad consectetur. Excepteur tempor labore sunt duis non ullamco laboris officia nulla consequat consequat irure elit aliquip. Reprehenderit excepteur ut reprehenderit non ipsum in elit incididunt aute laboris nulla. Nulla reprehenderit aute sunt excepteur aliqua reprehenderit adipisicing id eiusmod magna eu eu culpa sunt. Anim ea aliqua sit minim enim quis elit.\r\n",
            "rating": 3.2738
          }
        ],
        "recipeTypes3": [
          {
            "ingredients": [
              "sit",
              "magna",
              "reprehenderit",
              "ullamco",
              "cupidatat"
            ],
            "recipeName": "Lilia Stokes",
            "cookingMethos": "Consequat culpa Lorem reprehenderit enim do sint enim reprehenderit labore. Elit sunt est consequat voluptate est excepteur. Amet consequat anim sit enim anim exercitation proident. Dolore ullamco ipsum aute pariatur Lorem dolore labore minim sunt ullamco. Irure irure incididunt magna aute quis laborum ut et do. Do sunt voluptate cillum dolore officia officia cupidatat. Consequat ullamco aute enim cillum exercitation aliquip velit eu cupidatat nisi anim nisi ut do.\r\n",
            "rating": 4.0846
          }
        ]
      },
      {
        "id": 8,
        "picture": "http://placehold.it/32x32",
        "userPicture": "http://placehold.it/32x32",
        "userRating": 4.1947,
        "yearOfExperience": 10,
        "name": "Annie Meyers",
        "userName": "Susanne Whitfield",
        "userGender": "female",
        "Gender": "female",
        "company": "QUOTEZART",
        "email": "susannewhitfield@quotezart.com",
        "phone": "+1 (939) 519-2409",
        "address": "101 Moore Street, Cuylerville, Kansas",
        "about": "Consequat ad aliqua qui in do amet incididunt deserunt consectetur pariatur exercitation do pariatur. Adipisicing magna Lorem dolore consectetur eu laborum enim. Minim laborum amet exercitation anim. Officia occaecat velit aliquip cupidatat elit minim non incididunt elit in. Occaecat officia incididunt in et elit ipsum duis officia. Dolor proident irure consectetur ullamco nulla magna consectetur.\r\n",
        "userComment": "Cillum laborum pariatur anim do eiusmod. Dolor commodo occaecat cillum dolore anim ex dolor. Deserunt exercitation irure amet Lorem qui incididunt amet. Sint excepteur est tempor adipisicing. Aliqua nisi et ullamco proident veniam cupidatat aute culpa est. Eiusmod occaecat non reprehenderit minim proident nostrud. Magna excepteur qui ipsum non minim aliqua sint occaecat.\r\n",
        "numberOfRecife": 19,
        "like": 518,
        "eventDate": "2020-10-26T11:53:42 -06:00",
        "foodName": "Franklin Maynard",
        "newsTitle": "Kristi Bray",
        "recipeTypes1": [
          {
            "ingredients": [
              "deserunt",
              "ipsum",
              "consequat",
              "dolore",
              "irure"
            ],
            "recipeName": "Delores Yang",
            "cookingMethos": "Culpa cillum proident consequat ex ea aute amet anim aliquip nulla duis magna. Quis reprehenderit anim enim duis reprehenderit anim fugiat do nostrud in. Eiusmod sit consectetur deserunt sint reprehenderit occaecat quis officia excepteur esse sunt. Duis duis cupidatat et exercitation deserunt consectetur anim. Ullamco anim ea tempor incididunt laborum veniam minim occaecat reprehenderit tempor. Cillum ipsum proident pariatur minim et reprehenderit.\r\n",
            "rating": 4.4688
          }
        ],
        "recipeTypes2": [
          {
            "ingredients": [
              "elit",
              "sunt",
              "adipisicing",
              "commodo",
              "consequat"
            ],
            "recipeName": "Luisa Larson",
            "cookingMethos": "Tempor dolor reprehenderit nisi nulla enim est dolor nostrud duis proident ut non. Quis ipsum est proident tempor magna velit eu aute excepteur sit eiusmod reprehenderit. Voluptate velit occaecat ad non nostrud proident cupidatat aute eu. Nisi aute esse in est do. Fugiat quis Lorem eiusmod commodo aliqua consequat ad occaecat. Laborum laborum ullamco et excepteur esse Lorem in minim eiusmod. Quis consectetur qui eu in duis cupidatat adipisicing dolore.\r\n",
            "rating": 3.6922
          }
        ],
        "recipeTypes3": [
          {
            "ingredients": [
              "nisi",
              "nisi",
              "aute",
              "adipisicing",
              "magna"
            ],
            "recipeName": "Florine Hewitt",
            "cookingMethos": "Lorem voluptate ad id mollit non ullamco aliquip ex nulla. Excepteur adipisicing ipsum adipisicing ea duis reprehenderit eu eu nostrud. Labore veniam do elit incididunt commodo sit. Nostrud consectetur eiusmod in in do sit culpa sint non anim occaecat. Reprehenderit ad magna aliqua voluptate esse minim aliqua esse commodo.\r\n",
            "rating": 4.7026
          }
        ]
      }
]